fbknockknock/__init__.py
fbknockknock/fbknock.py
fbknockknock-0.2.dist-info/METADATA
fbknockknock-0.2.dist-info/WHEEL
fbknockknock-0.2.dist-info/top_level.txt
fbknockknock-0.2.dist-info/RECORD
