Metadata-Version: 2.1
Name: fbknockknock
Version: 0.2
Summary: fbknockknock
Home-page: https://github.com/ZIZUN/fbknockknock
Author: smlee
Author-email: cap1232@gmail.com
License: UNKNOWN
Download-URL: https://github.com/ZIZUN/fbknockknock/archive/0.0.tar.gz
Keywords: fbknockknock
Platform: UNKNOWN
Classifier: Programming Language :: Python :: 3
Classifier: Programming Language :: Python :: 3.2
Classifier: Programming Language :: Python :: 3.3
Classifier: Programming Language :: Python :: 3.4
Classifier: Programming Language :: Python :: 3.5
Classifier: Programming Language :: Python :: 3.6
Classifier: Programming Language :: Python :: 3.7
Requires-Dist: fbchat
